{
  "source": "C:\\Users\\engmo\\Desktop\\img\\Image-Processing\\dataset_images\\puzzle_2x2\\69.jpg",
  "rows": 2,
  "cols": 2,
  "bbox": [
    0,
    0,
    224,
    224
  ],
  "num_tiles_saved": 4,
  "tile_sizes": {
    "row_heights": [
      112,
      112
    ],
    "col_widths": [
      112,
      112
    ]
  },
  "tile_filenames": [
    "tile_00_00.png",
    "tile_00_01.png",
    "tile_01_00.png",
    "tile_01_01.png"
  ],
  "trim_info": {
    "tile_00_00.png": [
      0,
      0,
      0,
      0
    ],
    "tile_00_01.png": [
      0,
      0,
      0,
      0
    ],
    "tile_01_00.png": [
      0,
      0,
      0,
      0
    ],
    "tile_01_01.png": [
      0,
      0,
      0,
      0
    ]
  }
}